machineroom/__init__.py
machineroom/const.py
machineroom/errs.py
machineroom/infra.py
machineroom/schema.json
machineroom/sql.py
machineroom/taskbase.py
machineroom/util.py
machineroom/worker.py
machineroom/tunnels/__init__.py
machineroom/tunnels/conn.py
machineroom/tunnels/fork.py
machineroom-0.47.6.dist-info/LICENSE
machineroom-0.47.6.dist-info/METADATA
machineroom-0.47.6.dist-info/WHEEL
machineroom-0.47.6.dist-info/top_level.txt
machineroom-0.47.6.dist-info/RECORD
