Metadata-Version: 2.1
Name: machineroom
Version: 0.47.6
Summary: A Python package to manage all my machines in the fingertip.
Home-page: https://github.com/jjhesk/mymachineroom/
Author: Jun-You Liu & Heskemo
Author-email: meowmeow@gmail.com
License: MIT
Keywords: ssh machine room
Classifier: Development Status :: 3 - Alpha
Classifier: Intended Audience :: Developers
Classifier: License :: OSI Approved :: MIT License
Classifier: Programming Language :: Python :: 3.9
Classifier: Programming Language :: Python :: 3.11
Classifier: Programming Language :: Python :: 3.12
Classifier: Topic :: Software Development :: Code Generators
Classifier: Topic :: Software Development :: Libraries :: Python Modules
Requires-Python: >=3.8,<4
License-File: LICENSE
Requires-Dist: SQLiteAsJSON
Requires-Dist: fabric
Requires-Dist: pexpect
